[
  {
    "CategoryImage": "Assets\\崩坏三\\CategoryImage\\世界之星.png",
    "CategoryNameName": "世界之星"
  },
  {
    "CategoryImage": "Assets\\崩坏三\\CategoryImage\\无存之仪.png",
    "CategoryNameName": "无存之仪"
  },
  {
    "CategoryImage": "Assets\\崩坏三\\CategoryImage\\命运之轮.png",
    "CategoryNameName": "命运之轮"
  },
  {
    "CategoryImage": "Assets\\崩坏三\\CategoryImage\\升变之理.png",
    "CategoryNameName": "升变之理"
  },
  {
    "CategoryImage": "Assets\\崩坏三\\CategoryImage\\单角色.png",
    "CategoryNameName": "单角色"
  },
  {
    "CategoryImage": "Assets\\崩坏三\\CategoryImage\\琪亚娜.png",
    "CategoryNameName": "琪亚娜"
  },
  {
    "CategoryImage": "Assets\\崩坏三\\CategoryImage\\布洛妮娅.png",
    "CategoryNameName": "布洛妮娅"
  },
  {
    "CategoryImage": "Assets\\崩坏三\\CategoryImage\\雷电芽衣.png",
    "CategoryNameName": "雷电芽衣"
  },
  {
    "CategoryImage": "Assets\\崩坏三\\CategoryImage\\德莉莎.png",
    "CategoryNameName": "德莉莎"
  },
  {
    "CategoryImage": "Assets\\崩坏三\\CategoryImage\\无量塔姬子.png",
    "CategoryNameName": "无量塔姬子"
  },
  {
    "CategoryImage": "Assets\\崩坏三\\CategoryImage\\丽塔.png",
    "CategoryNameName": "丽塔"
  },
  {
    "CategoryImage": "Assets\\崩坏三\\CategoryImage\\卡莲.png",
    "CategoryNameName": "卡莲"
  },
  {
    "CategoryImage": "Assets\\崩坏三\\CategoryImage\\希儿.png",
    "CategoryNameName": "希儿"
  },
  {
    "CategoryImage": "Assets\\崩坏三\\CategoryImage\\幽兰黛尔.png",
    "CategoryNameName": "幽兰黛尔"
  },
  {
    "CategoryImage": "Assets\\崩坏三\\CategoryImage\\八重樱.png",
    "CategoryNameName": "八重樱"
  },
  {
    "CategoryImage": "Assets\\崩坏三\\CategoryImage\\阿琳姐妹.png",
    "CategoryNameName": "阿琳姐妹"
  },
  {
    "CategoryImage": "Assets\\崩坏三\\CategoryImage\\符华.png",
    "CategoryNameName": "符华"
  },
  {
    "CategoryImage": "Assets\\崩坏三\\CategoryImage\\逐火十三英桀.png",
    "CategoryNameName": "逐火十三英桀"
  },
  {
    "CategoryImage": "Assets\\崩坏三\\CategoryImage\\协同者.png",
    "CategoryNameName": "协同者"
  }
]